{
  "symbol": "GIGGLE",
  "risk_metrics_legend": "mean_rr = mean(win)/|mean(loss)| on per-bar signed returns (sign(p_system-P_now)*fwd_1, flat when tie); sharpe_per_bar = mean/sd of per-bar signed returns; sharpe_sample_window = sharpe_per_bar * sqrt(n_trade_rows); sharpe_annualized = sharpe_per_bar * sqrt(bars_per_year); calmar_proxy = compound total return / max drawdown on the same series; short val_bars => high variance / unstable interpretability. composite_norm (meta) zscore_within_run: cluster-level relative score only. composite_norm_final (default raw): final unseen rank_score equals comp_raw unless explicitly set to zscore_within_run (peer coupling on finalists). Why raw by default: few finalists share one unseen slice, so z-scoring peers mostly re-ranks noise and is easy to misread as skill; raw keeps an absolute leaderboard per formula. Neither leaks dev labels into unseen metrics; selection still uses dev-only meta.",
  "config": {
    "train_bars": 120,
    "val_bars": 36,
    "cycle_step": 20,
    "embargos": [
      12,
      24
    ],
    "shrinks": [
      0.94,
      0.95,
      0.96,
      0.97
    ],
    "trust_feature": "mean_pairwise_per_atr",
    "eval_gap_filter_column": null,
    "eval_gap_filter_min": null,
    "eval_gap_filter_max": null,
    "unseen_ratio": 0.25,
    "min_evals": 3,
    "top_k": 5,
    "bars_per_year": 8760.0,
    "rank_by": "composite",
    "composite_norm": "raw",
    "composite_norm_final": "raw",
    "cohort_top_fraction": 0.1,
    "cohort_sensitivity": false,
    "cohort_sensitivity_fractions": null,
    "composite_config": null,
    "composite_weights": {
      "w_mae": 0.4,
      "w_mae_tail": 0.0,
      "w_hit": 0.2,
      "w_rr": 0.15,
      "w_sharpe": 0.15,
      "w_calmar": 0.1
    },
    "reference_default_weight_preset": "balanced",
    "weights_equal_to_preset": "balanced"
  },
  "strict_unseen_guard": {
    "unseen_starts_at_index": 540,
    "final_eval_uses_unseen_slice_only": [
      0,
      180
    ],
    "unseen_used_in_discovery_or_meta_validation": false,
    "ranking_policy": {
      "meta_composite_norm": "raw",
      "final_composite_norm": "raw",
      "why_final_raw_default_ko": "최종 구간은 후보 수가 적고 동일 unseen 창을 공유하므로, 후보 간 z-score 랭킹은 '같은 잡음 창에서의 상대 순위'로 읽히기 쉬워 보고 편향이 생길 수 있다. raw는 각 공식의 절대 comp_raw만으로 순위를 매겨 해석이 직관적이고 peer coupling이 없다.",
      "note_ko": "메타는 dev 사이클 검증만 사용. 최종 unseen 지표는 동일 공식을 unseen 구간에만 적용해 산출. composite_norm_final=raw이면 최종 rank_score는 unseen에서만 계산한 comp_raw와 동일해 후보 간 z-score 정렬로 인한 수평 누설이 없음(명시적으로 zscore_within_run 선택 시만 해당)."
    }
  },
  "dev_cohort_top_fraction": {
    "n_eligible": 352,
    "fraction_used": 0.1,
    "top_n": 36,
    "rank_key": "composite_score",
    "cutoff_rank_score": 0.7645710546801545,
    "full_pool_rank_score_percentiles": {
      "p10": 0.3234204334765755,
      "p50": 0.43660250447028104,
      "p90": 0.7645710546801545
    },
    "top_bucket": {
      "directional_hit_rate": {
        "n": 36,
        "mean": 0.6355465476789006,
        "pstdev": 0.10392649460087482,
        "min": 0.4375,
        "max": 0.8
      },
      "mae_ratio_sys_over_naive": {
        "n": 36,
        "mean": 0.9282048508257983,
        "pstdev": 0.0826229696070962,
        "min": 0.6890497481374448,
        "max": 1.0021856960213131
      },
      "mean_rr": {
        "n": 36,
        "mean": 1.514200258492422,
        "pstdev": 0.9163597836791137,
        "min": 0.3925299880520473,
        "max": 3.3830075206345764
      },
      "sharpe_annualized": {
        "n": 36,
        "mean": 26.594783237491065,
        "pstdev": 10.64566496213247,
        "min": 10.91773432307705,
        "max": 41.892900845114326
      },
      "calmar_proxy": {
        "n": 32,
        "mean": 2.547172107326412,
        "pstdev": 1.770691409240231,
        "min": 0.933396450415519,
        "max": 5.719085687793188
      },
      "composite_score": {
        "n": 36,
        "mean": 0.8292421129509072,
        "pstdev": 0.05222452173802183,
        "min": 0.7645710546801545,
        "max": 0.9447074147302638
      }
    },
    "all_validations_baseline": {
      "directional_hit_rate": {
        "n": 352,
        "mean": 0.499686665872344,
        "pstdev": 0.09448572618111907,
        "min": 0.2,
        "max": 0.8
      },
      "mae_ratio_sys_over_naive": {
        "n": 352,
        "mean": 0.9957851651219409,
        "pstdev": 0.044130092778735475,
        "min": 0.6890497481374448,
        "max": 1.174463639516814
      }
    }
  },
  "counts": {
    "n_total_rows": 720,
    "n_dev_rows": 540,
    "n_unseen_rows": 180,
    "n_cycles": 19,
    "n_validations": 432,
    "n_clusters": 24,
    "n_selected_for_final": 5,
    "n_final_evals": 5
  },
  "meta_clusters": [
    {
      "cluster_key": "trust_low40|emb=12|sh=0.95|feat=mean_pairwise_per_atr|q=0.0-0.4",
      "n_eval": 18,
      "hit_mean": 0.5199624613900483,
      "mae_ratio_mean": 0.9910411577492799,
      "coverage_mean": 0.46296296296296297,
      "mean_rr_mean": 1.0621474545930643,
      "sharpe_mean": 0.014525187852030035,
      "sharpe_annualized_mean": 1.359483092766521,
      "calmar_mean": 0.42072455326281116,
      "composite_mean": 0.5657523819383885,
      "sample_formula": {
        "formula_id": "C0000-F0004",
        "family": "trust_low40",
        "system_col": "p_system_shrunk_custom",
        "shrink_weight": 0.95,
        "embargo_bars": 12,
        "trust_feature": "mean_pairwise_per_atr",
        "trust_q_low": 0.0,
        "trust_q_high": 0.4
      },
      "composite_rank_score": 0.5657523819383885
    },
    {
      "cluster_key": "trust_low40|emb=12|sh=0.94|feat=mean_pairwise_per_atr|q=0.0-0.4",
      "n_eval": 18,
      "hit_mean": 0.5199624613900483,
      "mae_ratio_mean": 0.9912971545758849,
      "coverage_mean": 0.46296296296296297,
      "mean_rr_mean": 1.0621474545930643,
      "sharpe_mean": 0.014525187852030035,
      "sharpe_annualized_mean": 1.359483092766521,
      "calmar_mean": 0.42072455326281116,
      "composite_mean": 0.5657298943870551,
      "sample_formula": {
        "formula_id": "C0000-F0001",
        "family": "trust_low40",
        "system_col": "p_system_shrunk_custom",
        "shrink_weight": 0.94,
        "embargo_bars": 12,
        "trust_feature": "mean_pairwise_per_atr",
        "trust_q_low": 0.0,
        "trust_q_high": 0.4
      },
      "composite_rank_score": 0.5657298943870551
    },
    {
      "cluster_key": "trust_low40|emb=12|sh=0.96|feat=mean_pairwise_per_atr|q=0.0-0.4",
      "n_eval": 18,
      "hit_mean": 0.5199624613900483,
      "mae_ratio_mean": 0.9918140907625652,
      "coverage_mean": 0.46296296296296297,
      "mean_rr_mean": 1.0621474545930643,
      "sharpe_mean": 0.014525187852030035,
      "sharpe_annualized_mean": 1.359483092766521,
      "calmar_mean": 0.42072455326281116,
      "composite_mean": 0.5653358299477228,
      "sample_formula": {
        "formula_id": "C0000-F0007",
        "family": "trust_low40",
        "system_col": "p_system_shrunk_custom",
        "shrink_weight": 0.96,
        "embargo_bars": 12,
        "trust_feature": "mean_pairwise_per_atr",
        "trust_q_low": 0.0,
        "trust_q_high": 0.4
      },
      "composite_rank_score": 0.5653358299477228
    },
    {
      "cluster_key": "trust_low40|emb=12|sh=0.97|feat=mean_pairwise_per_atr|q=0.0-0.4",
      "n_eval": 18,
      "hit_mean": 0.5199624613900483,
      "mae_ratio_mean": 0.9935479400874526,
      "coverage_mean": 0.46296296296296297,
      "mean_rr_mean": 1.0621474545930643,
      "sharpe_mean": 0.014525187852030035,
      "sharpe_annualized_mean": 1.359483092766521,
      "calmar_mean": 0.42072455326281116,
      "composite_mean": 0.5645193268060835,
      "sample_formula": {
        "formula_id": "C0000-F0010",
        "family": "trust_low40",
        "system_col": "p_system_shrunk_custom",
        "shrink_weight": 0.97,
        "embargo_bars": 12,
        "trust_feature": "mean_pairwise_per_atr",
        "trust_q_low": 0.0,
        "trust_q_high": 0.4
      },
      "composite_rank_score": 0.5645193268060835
    },
    {
      "cluster_key": "trust_high40|emb=12|sh=0.94|feat=mean_pairwise_per_atr|q=0.6-1.0",
      "n_eval": 18,
      "hit_mean": 0.5233991702741703,
      "mae_ratio_mean": 0.9953056478727563,
      "coverage_mean": 0.25308641975308643,
      "mean_rr_mean": 0.8898996138195552,
      "sharpe_mean": -0.061793766728371495,
      "sharpe_annualized_mean": -5.783579665982672,
      "calmar_mean": -0.024949271529482682,
      "composite_mean": 0.5495435027585447,
      "sample_formula": {
        "formula_id": "C0000-F0002",
        "family": "trust_high40",
        "system_col": "p_system_shrunk_custom",
        "shrink_weight": 0.94,
        "embargo_bars": 12,
        "trust_feature": "mean_pairwise_per_atr",
        "trust_q_low": 0.6,
        "trust_q_high": 1.0
      },
      "composite_rank_score": 0.5495435027585447
    },
    {
      "cluster_key": "trust_high40|emb=12|sh=0.95|feat=mean_pairwise_per_atr|q=0.6-1.0",
      "n_eval": 18,
      "hit_mean": 0.5233991702741703,
      "mae_ratio_mean": 0.9951257342958594,
      "coverage_mean": 0.25308641975308643,
      "mean_rr_mean": 0.8898996138195552,
      "sharpe_mean": -0.061793766728371495,
      "sharpe_annualized_mean": -5.783579665982672,
      "calmar_mean": -0.024949271529482682,
      "composite_mean": 0.5481893058600629,
      "sample_formula": {
        "formula_id": "C0000-F0005",
        "family": "trust_high40",
        "system_col": "p_system_shrunk_custom",
        "shrink_weight": 0.95,
        "embargo_bars": 12,
        "trust_feature": "mean_pairwise_per_atr",
        "trust_q_low": 0.6,
        "trust_q_high": 1.0
      },
      "composite_rank_score": 0.5481893058600629
    },
    {
      "cluster_key": "trust_high40|emb=12|sh=0.96|feat=mean_pairwise_per_atr|q=0.6-1.0",
      "n_eval": 18,
      "hit_mean": 0.5233991702741703,
      "mae_ratio_mean": 0.9949458207189614,
      "coverage_mean": 0.25308641975308643,
      "mean_rr_mean": 0.8898996138195552,
      "sharpe_mean": -0.061793766728371495,
      "sharpe_annualized_mean": -5.783579665982672,
      "calmar_mean": -0.024949271529482682,
      "composite_mean": 0.5471621954993043,
      "sample_formula": {
        "formula_id": "C0000-F0008",
        "family": "trust_high40",
        "system_col": "p_system_shrunk_custom",
        "shrink_weight": 0.96,
        "embargo_bars": 12,
        "trust_feature": "mean_pairwise_per_atr",
        "trust_q_low": 0.6,
        "trust_q_high": 1.0
      },
      "composite_rank_score": 0.5471621954993043
    },
    {
      "cluster_key": "trust_high40|emb=12|sh=0.97|feat=mean_pairwise_per_atr|q=0.6-1.0",
      "n_eval": 18,
      "hit_mean": 0.5233991702741703,
      "mae_ratio_mean": 0.9947659071420648,
      "coverage_mean": 0.25308641975308643,
      "mean_rr_mean": 0.8898996138195552,
      "sharpe_mean": -0.061793766728371495,
      "sharpe_annualized_mean": -5.783579665982672,
      "calmar_mean": -0.024949271529482682,
      "composite_mean": 0.5464279087029682,
      "sample_formula": {
        "formula_id": "C0000-F0011",
        "family": "trust_high40",
        "system_col": "p_system_shrunk_custom",
        "shrink_weight": 0.97,
        "embargo_bars": 12,
        "trust_feature": "mean_pairwise_per_atr",
        "trust_q_low": 0.6,
        "trust_q_high": 1.0
      },
      "composite_rank_score": 0.5464279087029682
    },
    {
      "cluster_key": "trust_high40|emb=24|sh=0.94|feat=mean_pairwise_per_atr|q=0.6-1.0",
      "n_eval": 18,
      "hit_mean": 0.512357978279031,
      "mae_ratio_mean": 0.9787650255824104,
      "coverage_mean": 0.24537037037037038,
      "mean_rr_mean": 0.8927561078758557,
      "sharpe_mean": -0.052044843778491515,
      "sharpe_annualized_mean": -4.871130473720208,
      "calmar_mean": -0.04872039920239395,
      "composite_mean": 0.5340473650250314,
      "sample_formula": {
        "formula_id": "C0000-F0014",
        "family": "trust_high40",
        "system_col": "p_system_shrunk_custom",
        "shrink_weight": 0.94,
        "embargo_bars": 24,
        "trust_feature": "mean_pairwise_per_atr",
        "trust_q_low": 0.6,
        "trust_q_high": 1.0
      },
      "composite_rank_score": 0.5340473650250314
    },
    {
      "cluster_key": "trust_low40|emb=24|sh=0.97|feat=mean_pairwise_per_atr|q=0.0-0.4",
      "n_eval": 18,
      "hit_mean": 0.46078849529191396,
      "mae_ratio_mean": 1.0007369826255454,
      "coverage_mean": 0.4675925925925926,
      "mean_rr_mean": 1.04845791041043,
      "sharpe_mean": -0.10260044529881349,
      "sharpe_annualized_mean": -9.60287550942476,
      "calmar_mean": 0.21172677726886976,
      "composite_mean": 0.5315216270614558,
      "sample_formula": {
        "formula_id": "C0000-F0022",
        "family": "trust_low40",
        "system_col": "p_system_shrunk_custom",
        "shrink_weight": 0.97,
        "embargo_bars": 24,
        "trust_feature": "mean_pairwise_per_atr",
        "trust_q_low": 0.0,
        "trust_q_high": 0.4
      },
      "composite_rank_score": 0.5315216270614558
    },
    {
      "cluster_key": "trust_low40|emb=24|sh=0.96|feat=mean_pairwise_per_atr|q=0.0-0.4",
      "n_eval": 18,
      "hit_mean": 0.46078849529191396,
      "mae_ratio_mean": 1.0014117467412638,
      "coverage_mean": 0.4675925925925926,
      "mean_rr_mean": 1.04845791041043,
      "sharpe_mean": -0.10260044529881349,
      "sharpe_annualized_mean": -9.60287550942476,
      "calmar_mean": 0.21172677726886976,
      "composite_mean": 0.5314078334275715,
      "sample_formula": {
        "formula_id": "C0000-F0019",
        "family": "trust_low40",
        "system_col": "p_system_shrunk_custom",
        "shrink_weight": 0.96,
        "embargo_bars": 24,
        "trust_feature": "mean_pairwise_per_atr",
        "trust_q_low": 0.0,
        "trust_q_high": 0.4
      },
      "composite_rank_score": 0.5314078334275715
    },
    {
      "cluster_key": "trust_low40|emb=24|sh=0.95|feat=mean_pairwise_per_atr|q=0.0-0.4",
      "n_eval": 18,
      "hit_mean": 0.46078849529191396,
      "mae_ratio_mean": 1.00237601973739,
      "coverage_mean": 0.4675925925925926,
      "mean_rr_mean": 1.04845791041043,
      "sharpe_mean": -0.10260044529881349,
      "sharpe_annualized_mean": -9.60287550942476,
      "calmar_mean": 0.21172677726886976,
      "composite_mean": 0.5312104445988123,
      "sample_formula": {
        "formula_id": "C0000-F0016",
        "family": "trust_low40",
        "system_col": "p_system_shrunk_custom",
        "shrink_weight": 0.95,
        "embargo_bars": 24,
        "trust_feature": "mean_pairwise_per_atr",
        "trust_q_low": 0.0,
        "trust_q_high": 0.4
      },
      "composite_rank_score": 0.5312104445988123
    },
    {
      "cluster_key": "trust_high40|emb=24|sh=0.95|feat=mean_pairwise_per_atr|q=0.6-1.0",
      "n_eval": 18,
      "hit_mean": 0.512357978279031,
      "mae_ratio_mean": 0.9817798938795137,
      "coverage_mean": 0.24537037037037038,
      "mean_rr_mean": 0.8927561078758557,
      "sharpe_mean": -0.052044843778491515,
      "sharpe_annualized_mean": -4.871130473720208,
      "calmar_mean": -0.04872039920239395,
      "composite_mean": 0.5307108326117012,
      "sample_formula": {
        "formula_id": "C0000-F0017",
        "family": "trust_high40",
        "system_col": "p_system_shrunk_custom",
        "shrink_weight": 0.95,
        "embargo_bars": 24,
        "trust_feature": "mean_pairwise_per_atr",
        "trust_q_low": 0.6,
        "trust_q_high": 1.0
      },
      "composite_rank_score": 0.5307108326117012
    },
    {
      "cluster_key": "trust_low40|emb=24|sh=0.94|feat=mean_pairwise_per_atr|q=0.0-0.4",
      "n_eval": 18,
      "hit_mean": 0.46078849529191396,
      "mae_ratio_mean": 1.004241711273506,
      "coverage_mean": 0.4675925925925926,
      "mean_rr_mean": 1.04845791041043,
      "sharpe_mean": -0.10260044529881349,
      "sharpe_annualized_mean": -9.60287550942476,
      "calmar_mean": 0.21172677726886976,
      "composite_mean": 0.5306538672347831,
      "sample_formula": {
        "formula_id": "C0000-F0013",
        "family": "trust_low40",
        "system_col": "p_system_shrunk_custom",
        "shrink_weight": 0.94,
        "embargo_bars": 24,
        "trust_feature": "mean_pairwise_per_atr",
        "trust_q_low": 0.0,
        "trust_q_high": 0.4
      },
      "composite_rank_score": 0.5306538672347831
    },
    {
      "cluster_key": "trust_high40|emb=24|sh=0.96|feat=mean_pairwise_per_atr|q=0.6-1.0",
      "n_eval": 18,
      "hit_mean": 0.512357978279031,
      "mae_ratio_mean": 0.9847947621766169,
      "coverage_mean": 0.24537037037037038,
      "mean_rr_mean": 0.8927561078758557,
      "sharpe_mean": -0.052044843778491515,
      "sharpe_annualized_mean": -4.871130473720208,
      "calmar_mean": -0.04872039920239395,
      "composite_mean": 0.5279335097496848,
      "sample_formula": {
        "formula_id": "C0000-F0020",
        "family": "trust_high40",
        "system_col": "p_system_shrunk_custom",
        "shrink_weight": 0.96,
        "embargo_bars": 24,
        "trust_feature": "mean_pairwise_per_atr",
        "trust_q_low": 0.6,
        "trust_q_high": 1.0
      },
      "composite_rank_score": 0.5279335097496848
    },
    {
      "cluster_key": "trust_high40|emb=24|sh=0.97|feat=mean_pairwise_per_atr|q=0.6-1.0",
      "n_eval": 18,
      "hit_mean": 0.512357978279031,
      "mae_ratio_mean": 0.9878096304737203,
      "coverage_mean": 0.24537037037037038,
      "mean_rr_mean": 0.8927561078758557,
      "sharpe_mean": -0.052044843778491515,
      "sharpe_annualized_mean": -4.871130473720208,
      "calmar_mean": -0.04872039920239395,
      "composite_mean": 0.5256178969437544,
      "sample_formula": {
        "formula_id": "C0000-F0023",
        "family": "trust_high40",
        "system_col": "p_system_shrunk_custom",
        "shrink_weight": 0.97,
        "embargo_bars": 24,
        "trust_feature": "mean_pairwise_per_atr",
        "trust_q_low": 0.6,
        "trust_q_high": 1.0
      },
      "composite_rank_score": 0.5256178969437544
    },
    {
      "cluster_key": "base|emb=12|sh=0.96",
      "n_eval": 18,
      "hit_mean": 0.5079831932773109,
      "mae_ratio_mean": 0.9949401515326355,
      "coverage_mean": 1.0,
      "mean_rr_mean": 0.9049350660673259,
      "sharpe_mean": -0.04112478085028252,
      "sharpe_annualized_mean": -3.8490685854967266,
      "calmar_mean": -0.10354840834452073,
      "composite_mean": 0.49506997447402884,
      "sample_formula": {
        "formula_id": "C0000-F0006",
        "family": "base",
        "system_col": "p_system_shrunk_custom",
        "shrink_weight": 0.96,
        "embargo_bars": 12,
        "trust_feature": null,
        "trust_q_low": null,
        "trust_q_high": null
      },
      "composite_rank_score": 0.49506997447402884
    },
    {
      "cluster_key": "base|emb=12|sh=0.97",
      "n_eval": 18,
      "hit_mean": 0.5079831932773109,
      "mae_ratio_mean": 0.9951543928177399,
      "coverage_mean": 1.0,
      "mean_rr_mean": 0.9049350660673259,
      "sharpe_mean": -0.04112478085028252,
      "sharpe_annualized_mean": -3.8490685854967266,
      "calmar_mean": -0.10354840834452073,
      "composite_mean": 0.4949381328576704,
      "sample_formula": {
        "formula_id": "C0000-F0009",
        "family": "base",
        "system_col": "p_system_shrunk_custom",
        "shrink_weight": 0.97,
        "embargo_bars": 12,
        "trust_feature": null,
        "trust_q_low": null,
        "trust_q_high": null
      },
      "composite_rank_score": 0.4949381328576704
    },
    {
      "cluster_key": "base|emb=12|sh=0.95",
      "n_eval": 18,
      "hit_mean": 0.5079831932773109,
      "mae_ratio_mean": 0.9961913915410049,
      "coverage_mean": 1.0,
      "mean_rr_mean": 0.9049350660673259,
      "sharpe_mean": -0.04112478085028252,
      "sharpe_annualized_mean": -3.8490685854967266,
      "calmar_mean": -0.10354840834452073,
      "composite_mean": 0.4946184725081187,
      "sample_formula": {
        "formula_id": "C0000-F0003",
        "family": "base",
        "system_col": "p_system_shrunk_custom",
        "shrink_weight": 0.95,
        "embargo_bars": 12,
        "trust_feature": null,
        "trust_q_low": null,
        "trust_q_high": null
      },
      "composite_rank_score": 0.4946184725081187
    },
    {
      "cluster_key": "base|emb=12|sh=0.94",
      "n_eval": 18,
      "hit_mean": 0.5079831932773109,
      "mae_ratio_mean": 0.9991841647183105,
      "coverage_mean": 1.0,
      "mean_rr_mean": 0.9049350660673259,
      "sharpe_mean": -0.04112478085028252,
      "sharpe_annualized_mean": -3.8490685854967266,
      "calmar_mean": -0.10354840834452073,
      "composite_mean": 0.4934847840919683,
      "sample_formula": {
        "formula_id": "C0000-F0000",
        "family": "base",
        "system_col": "p_system_shrunk_custom",
        "shrink_weight": 0.94,
        "embargo_bars": 12,
        "trust_feature": null,
        "trust_q_low": null,
        "trust_q_high": null
      },
      "composite_rank_score": 0.4934847840919683
    },
    {
      "cluster_key": "base|emb=24|sh=0.97",
      "n_eval": 18,
      "hit_mean": 0.4873482726423903,
      "mae_ratio_mean": 0.9978253162154136,
      "coverage_mean": 1.0,
      "mean_rr_mean": 0.8923665843645924,
      "sharpe_mean": -0.07823088319864703,
      "sharpe_annualized_mean": -7.322009472386219,
      "calmar_mean": -0.3094126348567239,
      "composite_mean": 0.4655836218742413,
      "sample_formula": {
        "formula_id": "C0000-F0021",
        "family": "base",
        "system_col": "p_system_shrunk_custom",
        "shrink_weight": 0.97,
        "embargo_bars": 24,
        "trust_feature": null,
        "trust_q_low": null,
        "trust_q_high": null
      },
      "composite_rank_score": 0.4655836218742413
    },
    {
      "cluster_key": "base|emb=24|sh=0.96",
      "n_eval": 18,
      "hit_mean": 0.4873482726423903,
      "mae_ratio_mean": 0.998519608978502,
      "coverage_mean": 1.0,
      "mean_rr_mean": 0.8923665843645924,
      "sharpe_mean": -0.07823088319864703,
      "sharpe_annualized_mean": -7.322009472386219,
      "calmar_mean": -0.3094126348567239,
      "composite_mean": 0.46535343519633354,
      "sample_formula": {
        "formula_id": "C0000-F0018",
        "family": "base",
        "system_col": "p_system_shrunk_custom",
        "shrink_weight": 0.96,
        "embargo_bars": 24,
        "trust_feature": null,
        "trust_q_low": null,
        "trust_q_high": null
      },
      "composite_rank_score": 0.46535343519633354
    },
    {
      "cluster_key": "base|emb=24|sh=0.95",
      "n_eval": 18,
      "hit_mean": 0.4873482726423903,
      "mae_ratio_mean": 1.0000457565716838,
      "coverage_mean": 1.0,
      "mean_rr_mean": 0.8923665843645924,
      "sharpe_mean": -0.07823088319864703,
      "sharpe_annualized_mean": -7.322009472386219,
      "calmar_mean": -0.3094126348567239,
      "composite_mean": 0.46480169082457395,
      "sample_formula": {
        "formula_id": "C0000-F0015",
        "family": "base",
        "system_col": "p_system_shrunk_custom",
        "shrink_weight": 0.95,
        "embargo_bars": 24,
        "trust_feature": null,
        "trust_q_low": null,
        "trust_q_high": null
      },
      "composite_rank_score": 0.46480169082457395
    },
    {
      "cluster_key": "base|emb=24|sh=0.94",
      "n_eval": 18,
      "hit_mean": 0.4873482726423903,
      "mae_ratio_mean": 1.0034225237885466,
      "coverage_mean": 1.0,
      "mean_rr_mean": 0.8923665843645924,
      "sharpe_mean": -0.07823088319864703,
      "sharpe_annualized_mean": -7.322009472386219,
      "calmar_mean": -0.3094126348567239,
      "composite_mean": 0.4635202533558608,
      "sample_formula": {
        "formula_id": "C0000-F0012",
        "family": "base",
        "system_col": "p_system_shrunk_custom",
        "shrink_weight": 0.94,
        "embargo_bars": 24,
        "trust_feature": null,
        "trust_q_low": null,
        "trust_q_high": null
      },
      "composite_rank_score": 0.4635202533558608
    }
  ],
  "final_unseen": [
    {
      "cluster_key": "base|emb=12|sh=0.96",
      "formula": {
        "formula_id": "C0000-F0006",
        "family": "base",
        "system_col": "p_system_shrunk_custom",
        "shrink_weight": 0.96,
        "embargo_bars": 12,
        "trust_feature": null,
        "trust_q_low": null,
        "trust_q_high": null
      },
      "metrics": {
        "n_used": 35,
        "directional_hit_rate": 0.48484848484848486,
        "mae_sys_next_close": 0.22066515391768268,
        "mae_naive_now_next_close": 0.21999999999999997,
        "mae_ratio_sys_over_naive": 1.0030234268985578,
        "mae_ratio_sys_over_naive_p90": 1.5776220294985912,
        "spearman_signed_sys_vs_fwd1": 0.37621682282889424,
        "system_col": "p_system_shrunk_custom",
        "shrink_weight": 0.96,
        "n_rows_validation": 36,
        "eval_gap_filter_active": false,
        "trust_coverage": 1.0,
        "n_selected": 36,
        "n_trade_rows": 33,
        "mean_rr": 0.5860578305126624,
        "sharpe_per_bar": -0.22967463376806319,
        "sharpe_sample_window": -1.3193803220013176,
        "sharpe_annualized": -21.49636786978877,
        "calmar_proxy": -0.7028376050164296,
        "strategy_mean_fwd": -0.0020594133597453008,
        "naive_mean_fwd": -0.002630334467538718,
        "regime_quintile_tables": {
          "mean_pairwise_per_atr": {
            "q5": [
              {
                "bucket": 0,
                "n": 8,
                "directional_hit_rate": 0.375,
                "mae_ratio_sys_over_naive": 1.0264738330829128,
                "spearman_signed_sys_vs_fwd1": -0.3571428571428572,
                "n_trade_rows": 8,
                "mean_rr": 0.7354729733637171,
                "sharpe_per_bar": -0.3399699323108237,
                "sharpe_sample_window": -0.9615801781460599,
                "sharpe_annualized": -31.819442180980044,
                "calmar_proxy": -0.5648256066334753,
                "strategy_mean_fwd": -0.0019562638756242534,
                "naive_mean_fwd": -0.004540080595604512
              },
              {
                "bucket": 1,
                "n": 7,
                "directional_hit_rate": 0.4,
                "mae_ratio_sys_over_naive": 1.070982711106819,
                "spearman_signed_sys_vs_fwd1": -0.5428571428571429,
                "n_trade_rows": 5,
                "mean_rr": 0.2796313562615442,
                "sharpe_per_bar": -0.6147727047498933,
                "sharpe_sample_window": -1.3746735585321694,
                "sharpe_annualized": -57.53957239768276,
                "calmar_proxy": -0.8176064726596758,
                "strategy_mean_fwd": -0.0053495424951458094,
                "naive_mean_fwd": -0.0050297073680245314
              },
              {
                "bucket": 2,
                "n": 7,
                "directional_hit_rate": 0.5714285714285714,
                "mae_ratio_sys_over_naive": 0.97115219953322,
                "spearman_signed_sys_vs_fwd1": 0.6071428571428572,
                "n_trade_rows": 7,
                "mean_rr": 0.5157195773010169,
                "sharpe_per_bar": -0.14669272490094473,
                "sharpe_sample_window": -0.38811246923031184,
                "sharpe_annualized": -13.729686759735301,
                "calmar_proxy": -0.3756989353530376,
                "strategy_mean_fwd": -0.002077770673518902,
                "naive_mean_fwd": -0.002077770673518902
              },
              {
                "bucket": 3,
                "n": 7,
                "directional_hit_rate": 0.6666666666666666,
                "mae_ratio_sys_over_naive": 0.9517004167741696,
                "spearman_signed_sys_vs_fwd1": 0.1785714285714286,
                "n_trade_rows": 6,
                "mean_rr": 0.2353994622789288,
                "sharpe_per_bar": -0.27365465647835957,
                "sharpe_sample_window": -0.6703142741085959,
                "sharpe_annualized": -25.61267245071571,
                "calmar_proxy": -1.1003358196520308,
                "strategy_mean_fwd": -0.0020048870470599223,
                "naive_mean_fwd": -0.0017184746117656477
              },
              {
                "bucket": 4,
                "n": 7,
                "directional_hit_rate": 0.42857142857142855,
                "mae_ratio_sys_over_naive": 1.014536446339548,
                "spearman_signed_sys_vs_fwd1": 0.3571428571428572,
                "n_trade_rows": 7,
                "mean_rr": 1.3963834815303457,
                "sharpe_per_bar": 0.016182437480071962,
                "sharpe_sample_window": 0.042814705179121164,
                "sharpe_annualized": 1.5145931590023756,
                "calmar_proxy": 0.038631045241797994,
                "strategy_mean_fwd": 0.00014441422944571386,
                "naive_mean_fwd": 0.00014441422944571386
              }
            ],
            "q10": [],
            "tails_10_20": [
              {
                "bucket": "bottom_20pct",
                "n": 8,
                "directional_hit_rate": 0.375,
                "mae_ratio_sys_over_naive": 1.0264738330829128,
                "spearman_signed_sys_vs_fwd1": -0.3571428571428572,
                "n_trade_rows": 8,
                "mean_rr": 0.7354729733637171,
                "sharpe_per_bar": -0.3399699323108237,
                "sharpe_sample_window": -0.9615801781460599,
                "sharpe_annualized": -31.819442180980044,
                "calmar_proxy": -0.5648256066334753,
                "strategy_mean_fwd": -0.0019562638756242534,
                "naive_mean_fwd": -0.004540080595604512
              },
              {
                "bucket": "top_20pct",
                "n": 8,
                "directional_hit_rate": 0.5,
                "mae_ratio_sys_over_naive": 0.9849073783063851,
                "spearman_signed_sys_vs_fwd1": 0.09523809523809526,
                "n_trade_rows": 8,
                "mean_rr": 1.2530333004501415,
                "sharpe_per_bar": 0.08051499791345709,
                "sharpe_sample_window": 0.22773080404730495,
                "sharpe_annualized": 7.535790895962749,
                "calmar_proxy": 0.25851310136288896,
                "strategy_mean_fwd": 0.0006761582409000877,
                "naive_mean_fwd": 0.0006761582409000877
              }
            ]
          },
          "p_system_tension": {
            "q5": [
              {
                "bucket": 0,
                "n": 8,
                "directional_hit_rate": 0.5,
                "mae_ratio_sys_over_naive": 1.0195419685743938,
                "spearman_signed_sys_vs_fwd1": 0.10714285714285716,
                "n_trade_rows": 6,
                "mean_rr": 1.303729071751585,
                "sharpe_per_bar": 0.10445727633165929,
                "sharpe_sample_window": 0.2558670269334674,
                "sharpe_annualized": 9.776665371627832,
                "calmar_proxy": 0.5655937730093389,
                "strategy_mean_fwd": 0.0009246486418273044,
                "naive_mean_fwd": 0.0007925559787091181
              },
              {
                "bucket": 1,
                "n": 7,
                "directional_hit_rate": 0.6666666666666666,
                "mae_ratio_sys_over_naive": 0.9374105246645076,
                "spearman_signed_sys_vs_fwd1": 0.6071428571428572,
                "n_trade_rows": 6,
                "mean_rr": 0.1726626949954316,
                "sharpe_per_bar": -0.3247157660114973,
                "sharpe_sample_window": -0.7953879381651452,
                "sharpe_annualized": -30.391730444000014,
                "calmar_proxy": -2.3985612780793812,
                "strategy_mean_fwd": -0.0034837213449247506,
                "naive_mean_fwd": -0.0029860468670783575
              },
              {
                "bucket": 2,
                "n": 7,
                "directional_hit_rate": 0.5714285714285714,
                "mae_ratio_sys_over_naive": 0.9649011369961129,
                "spearman_signed_sys_vs_fwd1": 0.21428571428571433,
                "n_trade_rows": 7,
                "mean_rr": 0.7395389372399934,
                "sharpe_per_bar": -0.0049098665735207185,
                "sharpe_sample_window": -0.01299028592404465,
                "sharpe_annualized": -0.4595383317888057,
                "calmar_proxy": -0.05613872594421474,
                "strategy_mean_fwd": -4.7767333453336515e-05,
                "naive_mean_fwd": -4.7767333453336515e-05
              },
              {
                "bucket": 3,
                "n": 7,
                "directional_hit_rate": 0.14285714285714285,
                "mae_ratio_sys_over_naive": 1.0599233966874555,
                "spearman_signed_sys_vs_fwd1": 0.1785714285714286,
                "n_trade_rows": 7,
                "mean_rr": 1.039041081901532,
                "sharpe_per_bar": -0.7821817483487562,
                "sharpe_sample_window": -2.0694583861845155,
                "sharpe_annualized": -73.20820034710096,
                "calmar_proxy": -1.0877949084916292,
                "strategy_mean_fwd": -0.007532164081564985,
                "naive_mean_fwd": -0.007532164081564985
              },
              {
                "bucket": 4,
                "n": 7,
                "directional_hit_rate": 0.5714285714285714,
                "mae_ratio_sys_over_naive": 0.9880271209918255,
                "spearman_signed_sys_vs_fwd1": 0.0,
                "n_trade_rows": 7,
                "mean_rr": 0.7749573819309856,
                "sharpe_per_bar": 0.013124340748138195,
                "sharpe_sample_window": 0.03472374174124506,
                "sharpe_annualized": 1.2283709878703535,
                "calmar_proxy": 0.028016352239694845,
                "strategy_mean_fwd": 6.475932173114327e-05,
                "naive_mean_fwd": -0.0033782500343060295
              }
            ],
            "q10": [],
            "tails_10_20": [
              {
                "bucket": "bottom_20pct",
                "n": 8,
                "directional_hit_rate": 0.5,
                "mae_ratio_sys_over_naive": 1.0195419685743938,
                "spearman_signed_sys_vs_fwd1": 0.10714285714285716,
                "n_trade_rows": 6,
                "mean_rr": 1.303729071751585,
                "sharpe_per_bar": 0.10445727633165929,
                "sharpe_sample_window": 0.2558670269334674,
                "sharpe_annualized": 9.776665371627832,
                "calmar_proxy": 0.5655937730093389,
                "strategy_mean_fwd": 0.0009246486418273044,
                "naive_mean_fwd": 0.0007925559787091181
              },
              {
                "bucket": "top_20pct",
                "n": 8,
                "directional_hit_rate": 0.5,
                "mae_ratio_sys_over_naive": 1.0056258676605214,
                "spearman_signed_sys_vs_fwd1": -0.07142857142857144,
                "n_trade_rows": 8,
                "mean_rr": 0.7814015050154972,
                "sharpe_per_bar": -0.10186156103939085,
                "sharpe_sample_window": -0.28810800221280286,
                "sharpe_annualized": -9.533719731996655,
                "calmar_proxy": -0.2241192780819864,
                "strategy_mean_fwd": -0.0004922231813072608,
                "naive_mean_fwd": -0.003504856367839787
              }
            ]
          }
        },
        "composite_score": 0.35169138875372447,
        "composite_rank_score": 0.35169138875372447
      }
    },
    {
      "cluster_key": "trust_low40|emb=12|sh=0.97|feat=mean_pairwise_per_atr|q=0.0-0.4",
      "formula": {
        "formula_id": "C0000-F0010",
        "family": "trust_low40",
        "system_col": "p_system_shrunk_custom",
        "shrink_weight": 0.97,
        "embargo_bars": 12,
        "trust_feature": "mean_pairwise_per_atr",
        "trust_q_low": 0.0,
        "trust_q_high": 0.4
      },
      "metrics": {
        "n_used": 11,
        "directional_hit_rate": 0.45454545454545453,
        "mae_sys_next_close": 0.1733742377574656,
        "mae_naive_now_next_close": 0.17090909090909048,
        "mae_ratio_sys_over_naive": 1.0144237315596416,
        "mae_ratio_sys_over_naive_p90": 1.0848672064030855,
        "spearman_signed_sys_vs_fwd1": -0.21818181818181823,
        "system_col": "p_system_shrunk_custom",
        "shrink_weight": 0.97,
        "n_rows_validation": 36,
        "eval_gap_filter_active": false,
        "trust_coverage": 0.3333333333333333,
        "n_selected": 12,
        "n_trade_rows": 11,
        "mean_rr": 0.6058221126063905,
        "sharpe_per_bar": -0.2873689574686915,
        "sharpe_sample_window": -0.9530950083192488,
        "sharpe_annualized": -26.896260691735375,
        "calmar_proxy": -0.5027635193689723,
        "strategy_mean_fwd": -0.0016485667803705487,
        "naive_mean_fwd": -0.003839572734212386,
        "composite_score": 0.3485039603499534,
        "composite_rank_score": 0.3485039603499534
      }
    },
    {
      "cluster_key": "trust_low40|emb=12|sh=0.96|feat=mean_pairwise_per_atr|q=0.0-0.4",
      "formula": {
        "formula_id": "C0000-F0007",
        "family": "trust_low40",
        "system_col": "p_system_shrunk_custom",
        "shrink_weight": 0.96,
        "embargo_bars": 12,
        "trust_feature": "mean_pairwise_per_atr",
        "trust_q_low": 0.0,
        "trust_q_high": 0.4
      },
      "metrics": {
        "n_used": 11,
        "directional_hit_rate": 0.45454545454545453,
        "mae_sys_next_close": 0.1741959533735905,
        "mae_naive_now_next_close": 0.17090909090909048,
        "mae_ratio_sys_over_naive": 1.0192316420795215,
        "mae_ratio_sys_over_naive_p90": 1.1131562752041224,
        "spearman_signed_sys_vs_fwd1": -0.21818181818181823,
        "system_col": "p_system_shrunk_custom",
        "shrink_weight": 0.96,
        "n_rows_validation": 36,
        "eval_gap_filter_active": false,
        "trust_coverage": 0.3333333333333333,
        "n_selected": 12,
        "n_trade_rows": 11,
        "mean_rr": 0.6058221126063905,
        "sharpe_per_bar": -0.2873689574686915,
        "sharpe_sample_window": -0.9530950083192488,
        "sharpe_annualized": -26.896260691735375,
        "calmar_proxy": -0.5027635193689723,
        "strategy_mean_fwd": -0.0016485667803705487,
        "naive_mean_fwd": -0.003839572734212386,
        "composite_score": 0.3466439127029641,
        "composite_rank_score": 0.3466439127029641
      }
    },
    {
      "cluster_key": "trust_low40|emb=12|sh=0.95|feat=mean_pairwise_per_atr|q=0.0-0.4",
      "formula": {
        "formula_id": "C0000-F0004",
        "family": "trust_low40",
        "system_col": "p_system_shrunk_custom",
        "shrink_weight": 0.95,
        "embargo_bars": 12,
        "trust_feature": "mean_pairwise_per_atr",
        "trust_q_low": 0.0,
        "trust_q_high": 0.4
      },
      "metrics": {
        "n_used": 11,
        "directional_hit_rate": 0.45454545454545453,
        "mae_sys_next_close": 0.17501766898971607,
        "mae_naive_now_next_close": 0.17090909090909048,
        "mae_ratio_sys_over_naive": 1.024039552599405,
        "mae_ratio_sys_over_naive_p90": 1.141445344005159,
        "spearman_signed_sys_vs_fwd1": -0.21818181818181823,
        "system_col": "p_system_shrunk_custom",
        "shrink_weight": 0.95,
        "n_rows_validation": 36,
        "eval_gap_filter_active": false,
        "trust_coverage": 0.3333333333333333,
        "n_selected": 12,
        "n_trade_rows": 11,
        "mean_rr": 0.6058221126063905,
        "sharpe_per_bar": -0.2873689574686915,
        "sharpe_sample_window": -0.9530950083192488,
        "sharpe_annualized": -26.896260691735375,
        "calmar_proxy": -0.5027635193689723,
        "strategy_mean_fwd": -0.0016485667803705487,
        "naive_mean_fwd": -0.003839572734212386,
        "composite_score": 0.34480133106620064,
        "composite_rank_score": 0.34480133106620064
      }
    },
    {
      "cluster_key": "trust_low40|emb=12|sh=0.94|feat=mean_pairwise_per_atr|q=0.0-0.4",
      "formula": {
        "formula_id": "C0000-F0001",
        "family": "trust_low40",
        "system_col": "p_system_shrunk_custom",
        "shrink_weight": 0.94,
        "embargo_bars": 12,
        "trust_feature": "mean_pairwise_per_atr",
        "trust_q_low": 0.0,
        "trust_q_high": 0.4
      },
      "metrics": {
        "n_used": 11,
        "directional_hit_rate": 0.45454545454545453,
        "mae_sys_next_close": 0.1758393846058394,
        "mae_naive_now_next_close": 0.17090909090909048,
        "mae_ratio_sys_over_naive": 1.0288474631192757,
        "mae_ratio_sys_over_naive_p90": 1.1697344128061957,
        "spearman_signed_sys_vs_fwd1": -0.21818181818181823,
        "system_col": "p_system_shrunk_custom",
        "shrink_weight": 0.94,
        "n_rows_validation": 36,
        "eval_gap_filter_active": false,
        "trust_coverage": 0.3333333333333333,
        "n_selected": 12,
        "n_trade_rows": 11,
        "mean_rr": 0.6058221126063905,
        "sharpe_per_bar": -0.2873689574686915,
        "sharpe_sample_window": -0.9530950083192488,
        "sharpe_annualized": -26.896260691735375,
        "calmar_proxy": -0.5027635193689723,
        "strategy_mean_fwd": -0.0016485667803705487,
        "naive_mean_fwd": -0.003839572734212386,
        "composite_score": 0.34297597057825707,
        "composite_rank_score": 0.34297597057825707
      }
    }
  ]
}